daggerml_cli/__about__.py
daggerml_cli/__init__.py
daggerml_cli/__main__.py
daggerml_cli/api.py
daggerml_cli/config.py
daggerml_cli/db.py
daggerml_cli/pack.py
daggerml_cli/python_fork_adapter.py
daggerml_cli/repo.py
daggerml_cli/topology.py
daggerml_cli/util.py
daggerml_cli/cli/__init__.py
daggerml_cli-0.0.38.post1.dist-info/METADATA
daggerml_cli-0.0.38.post1.dist-info/WHEEL
daggerml_cli-0.0.38.post1.dist-info/entry_points.txt
daggerml_cli-0.0.38.post1.dist-info/licenses/LICENSE.txt
daggerml_cli-0.0.38.post1.dist-info/RECORD
