Metadata-Version: 2.4
Name: daggerml-cli
Version: 0.0.38.post1
Summary: DaggerML's cli backend
Project-URL: Homepage, https://daggerml.com
Project-URL: Documentation, https://daggerml.com
Project-URL: Issues, https://github.com/daggerml/daggerml-cli/issues
Project-URL: Source, https://github.com/daggerml/daggerml-cli
Author-email: Micha Niskin <micha.niskin@gmail.com>
License-Expression: MIT
License-File: LICENSE.txt
Classifier: Development Status :: 4 - Beta
Classifier: License :: OSI Approved :: MIT License
Classifier: Operating System :: OS Independent
Classifier: Programming Language :: Python
Classifier: Programming Language :: Python :: 3
Classifier: Programming Language :: Python :: 3.9
Classifier: Programming Language :: Python :: 3.10
Classifier: Programming Language :: Python :: 3.11
Classifier: Programming Language :: Python :: 3.12
Classifier: Programming Language :: Python :: 3.13
Classifier: Programming Language :: Python :: Implementation :: PyPy
Requires-Python: >=3.9
Requires-Dist: asciidag
Requires-Dist: click
Requires-Dist: jmespath
Requires-Dist: lmdb
Requires-Dist: msgpack
Requires-Dist: tabulate
Provides-Extra: test
Requires-Dist: pytest; extra == 'test'
Requires-Dist: pytest-cov; extra == 'test'
